[{"route":"/NA","file_path":"content/data/NA.json","name_iso_en":"North America"},{"route":"/NA/AG","file_path":"content/data/NA/AG.json","name_iso_en":"Antigua and Barbuda"},{"route":"/NA/AW","file_path":"content/data/NA/AW.json","name_iso_en":"Aruba"},{"route":"/NA/BS","file_path":"content/data/NA/BS.json","name_iso_en":"Bahamas"},{"route":"/NA/BB","file_path":"content/data/NA/BB.json","name_iso_en":"Barbados"},{"route":"/NA/BZ","file_path":"content/data/NA/BZ.json","name_iso_en":"Belize"},{"route":"/NA/BM","file_path":"content/data/NA/BM.json","name_iso_en":"Bermuda"},{"route":"/NA/BQ","file_path":"content/data/NA/BQ.json","name_iso_en":"Bonaire, Sint Eustatius and Saba"},{"route":"/NA/CA","file_path":"content/data/NA/CA.json","name_iso_en":"Canada"},{"route":"/NA/KY","file_path":"content/data/NA/KY.json","name_iso_en":"Cayman Islands"},{"route":"/NA/CR","file_path":"content/data/NA/CR.json","name_iso_en":"Costa Rica"},{"route":"/NA/CU","file_path":"content/data/NA/CU.json","name_iso_en":"Cuba"},{"route":"/NA/CW","file_path":"content/data/NA/CW.json","name_iso_en":"Curacao"},{"route":"/NA/DM","file_path":"content/data/NA/DM.json","name_iso_en":"Dominica"},{"route":"/NA/DO","file_path":"content/data/NA/DO.json","name_iso_en":"Dominican Republic"},{"route":"/NA/SV","file_path":"content/data/NA/SV.json","name_iso_en":"El Salvador"},{"route":"/NA/GL","file_path":"content/data/NA/GL.json","name_iso_en":"Greenland"},{"route":"/NA/GD","file_path":"content/data/NA/GD.json","name_iso_en":"Grenada"},{"route":"/NA/GP","file_path":"content/data/NA/GP.json","name_iso_en":"Guadeloupe"},{"route":"/NA/GT","file_path":"content/data/NA/GT.json","name_iso_en":"Guatemala"},{"route":"/NA/HT","file_path":"content/data/NA/HT.json","name_iso_en":"Haiti"},{"route":"/NA/HN","file_path":"content/data/NA/HN.json","name_iso_en":"Honduras"},{"route":"/NA/JM","file_path":"content/data/NA/JM.json","name_iso_en":"Jamaica"},{"route":"/NA/MQ","file_path":"content/data/NA/MQ.json","name_iso_en":"Martinique"},{"route":"/NA/MX","file_path":"content/data/NA/MX.json","name_iso_en":"Mexico"},{"route":"/NA/MS","file_path":"content/data/NA/MS.json","name_iso_en":"Montserrat"},{"route":"/NA/NI","file_path":"content/data/NA/NI.json","name_iso_en":"Nicaragua"},{"route":"/NA/PA","file_path":"content/data/NA/PA.json","name_iso_en":"Panama"},{"route":"/NA/PR","file_path":"content/data/NA/PR.json","name_iso_en":"Puerto Rico"},{"route":"/NA/BL","file_path":"content/data/NA/BL.json","name_iso_en":"Saint Barthelemy"},{"route":"/NA/KN","file_path":"content/data/NA/KN.json","name_iso_en":"Saint Kitts and Nevis"},{"route":"/NA/LC","file_path":"content/data/NA/LC.json","name_iso_en":"Saint Lucia"},{"route":"/NA/MF","file_path":"content/data/NA/MF.json","name_iso_en":"Saint Martin (French part)"},{"route":"/NA/PM","file_path":"content/data/NA/PM.json","name_iso_en":"Saint Pierre and Miquelon"},{"route":"/NA/VC","file_path":"content/data/NA/VC.json","name_iso_en":"Saint Vincent and The Grenadines"},{"route":"/NA/SX","file_path":"content/data/NA/SX.json","name_iso_en":"Sint Maarten (Dutch part)"},{"route":"/NA/TT","file_path":"content/data/NA/TT.json","name_iso_en":"Trinidad and Tobago"},{"route":"/NA/TC","file_path":"content/data/NA/TC.json","name_iso_en":"Turks and Caicos Islands"},{"route":"/NA/US","file_path":"content/data/NA/US.json","name_iso_en":"United States"},{"route":"/NA/VG","file_path":"content/data/NA/VG.json","name_iso_en":"Virgin Islands, British"},{"route":"/NA/VI","file_path":"content/data/NA/VI.json","name_iso_en":"Virgin Islands, U.S."},{"route":"/AN","file_path":"content/data/AN.json","name_iso_en":"Antarctica"},{"route":"/AN/BV","file_path":"content/data/AN/BV.json","name_iso_en":"Bouvet Island"},{"route":"/AN/TF","file_path":"content/data/AN/TF.json","name_iso_en":"French Southern Territories"},{"route":"/AN/GS","file_path":"content/data/AN/GS.json","name_iso_en":"South Georgia and the South Sandwich Islands"},{"route":"/SA","file_path":"content/data/SA.json","name_iso_en":"South America"},{"route":"/SA/BO","file_path":"content/data/SA/BO.json","name_iso_en":"Bolivia, Plurinational State of"},{"route":"/SA/BR","file_path":"content/data/SA/BR.json","name_iso_en":"Brazil"},{"route":"/SA/CL","file_path":"content/data/SA/CL.json","name_iso_en":"Chile"},{"route":"/SA/CO","file_path":"content/data/SA/CO.json","name_iso_en":"Colombia"},{"route":"/SA/EC","file_path":"content/data/SA/EC.json","name_iso_en":"Ecuador"},{"route":"/SA/FK","file_path":"content/data/SA/FK.json","name_iso_en":"Falkland Islands (Malvinas)"},{"route":"/SA/GF","file_path":"content/data/SA/GF.json","name_iso_en":"French Guiana"},{"route":"/SA/GY","file_path":"content/data/SA/GY.json","name_iso_en":"Guyana"},{"route":"/SA/PY","file_path":"content/data/SA/PY.json","name_iso_en":"Paraguay"},{"route":"/SA/PE","file_path":"content/data/SA/PE.json","name_iso_en":"Peru"},{"route":"/SA/SR","file_path":"content/data/SA/SR.json","name_iso_en":"Suriname"},{"route":"/SA/UY","file_path":"content/data/SA/UY.json","name_iso_en":"Uruguay"},{"route":"/SA/VE","file_path":"content/data/SA/VE.json","name_iso_en":"Venezuela, Bolivarian Republic of"},{"route":"/AS","file_path":"content/data/AS.json","name_iso_en":"Asia"},{"route":"/AS/AM","file_path":"content/data/AS/AM.json","name_iso_en":"Armenia"},{"route":"/AS/AZ","file_path":"content/data/AS/AZ.json","name_iso_en":"Azerbaijan"},{"route":"/AS/BH","file_path":"content/data/AS/BH.json","name_iso_en":"Bahrain"},{"route":"/AS/BD","file_path":"content/data/AS/BD.json","name_iso_en":"Bangladesh"},{"route":"/AS/BT","file_path":"content/data/AS/BT.json","name_iso_en":"Bhutan"},{"route":"/AS/IO","file_path":"content/data/AS/IO.json","name_iso_en":"British Indian Ocean Territory"},{"route":"/AS/BN","file_path":"content/data/AS/BN.json","name_iso_en":"Brunei Darussalam"},{"route":"/AS/KH","file_path":"content/data/AS/KH.json","name_iso_en":"Cambodia"},{"route":"/AS/CN","file_path":"content/data/AS/CN.json","name_iso_en":"China"},{"route":"/AS/CX","file_path":"content/data/AS/CX.json","name_iso_en":"Christmas Island"},{"route":"/AS/CC","file_path":"content/data/AS/CC.json","name_iso_en":"Cocos (Keeling) Islands"},{"route":"/AS/CY","file_path":"content/data/AS/CY.json","name_iso_en":"Cyprus"},{"route":"/AS/GE","file_path":"content/data/AS/GE.json","name_iso_en":"Georgia"},{"route":"/AS/HK","file_path":"content/data/AS/HK.json","name_iso_en":"Hong Kong"},{"route":"/AS/IN","file_path":"content/data/AS/IN.json","name_iso_en":"India"},{"route":"/AS/ID","file_path":"content/data/AS/ID.json","name_iso_en":"Indonesia"},{"route":"/AS/IR","file_path":"content/data/AS/IR.json","name_iso_en":"Iran, Islamic Republic of"},{"route":"/AS/IQ","file_path":"content/data/AS/IQ.json","name_iso_en":"Iraq"},{"route":"/AS/IL","file_path":"content/data/AS/IL.json","name_iso_en":"Israel"},{"route":"/AS/JP","file_path":"content/data/AS/JP.json","name_iso_en":"Japan"},{"route":"/AS/JO","file_path":"content/data/AS/JO.json","name_iso_en":"Jordan"},{"route":"/AS/KZ","file_path":"content/data/AS/KZ.json","name_iso_en":"Kazakhstan"},{"route":"/AS/KP","file_path":"content/data/AS/KP.json","name_iso_en":"Korea, Democratic People's Republic of"},{"route":"/AS/KR","file_path":"content/data/AS/KR.json","name_iso_en":"Korea, Republic of"},{"route":"/AS/KW","file_path":"content/data/AS/KW.json","name_iso_en":"Kuwait"},{"route":"/AS/KG","file_path":"content/data/AS/KG.json","name_iso_en":"Kyrgyzstan"},{"route":"/AS/LA","file_path":"content/data/AS/LA.json","name_iso_en":"Lao People's Democratic Republic"},{"route":"/AS/LB","file_path":"content/data/AS/LB.json","name_iso_en":"Lebanon"},{"route":"/AS/MO","file_path":"content/data/AS/MO.json","name_iso_en":"Macao"},{"route":"/AS/MY","file_path":"content/data/AS/MY.json","name_iso_en":"Malaysia"},{"route":"/AS/MV","file_path":"content/data/AS/MV.json","name_iso_en":"Maldives"},{"route":"/AS/MN","file_path":"content/data/AS/MN.json","name_iso_en":"Mongolia"},{"route":"/AS/MM","file_path":"content/data/AS/MM.json","name_iso_en":"Myanmar"},{"route":"/AS/NP","file_path":"content/data/AS/NP.json","name_iso_en":"Nepal"},{"route":"/AS/PS","file_path":"content/data/AS/PS.json","name_iso_en":"Occupied Palestinian Territory"},{"route":"/AS/OM","file_path":"content/data/AS/OM.json","name_iso_en":"Oman"},{"route":"/AS/PK","file_path":"content/data/AS/PK.json","name_iso_en":"Pakistan"},{"route":"/AS/PH","file_path":"content/data/AS/PH.json","name_iso_en":"Philippines"},{"route":"/AS/QA","file_path":"content/data/AS/QA.json","name_iso_en":"Qatar"},{"route":"/AS/SA","file_path":"content/data/AS/SA.json","name_iso_en":"Saudi Arabia"},{"route":"/AS/SG","file_path":"content/data/AS/SG.json","name_iso_en":"Singapore"},{"route":"/AS/LK","file_path":"content/data/AS/LK.json","name_iso_en":"Sri Lanka"},{"route":"/AS/SY","file_path":"content/data/AS/SY.json","name_iso_en":"Syrian Arab Republic"},{"route":"/AS/TW","file_path":"content/data/AS/TW.json","name_iso_en":"Taiwan, Province of China"},{"route":"/AS/TJ","file_path":"content/data/AS/TJ.json","name_iso_en":"Tajikistan"},{"route":"/AS/TH","file_path":"content/data/AS/TH.json","name_iso_en":"Thailand"},{"route":"/AS/TL","file_path":"content/data/AS/TL.json","name_iso_en":"Timor-Leste"},{"route":"/AS/TR","file_path":"content/data/AS/TR.json","name_iso_en":"Turkey"},{"route":"/AS/TM","file_path":"content/data/AS/TM.json","name_iso_en":"Turkmenistan"},{"route":"/AS/AE","file_path":"content/data/AS/AE.json","name_iso_en":"United Arab Emirates"},{"route":"/AS/UZ","file_path":"content/data/AS/UZ.json","name_iso_en":"Uzbekistan"},{"route":"/AS/VN","file_path":"content/data/AS/VN.json","name_iso_en":"Viet Nam"},{"route":"/AS/YE","file_path":"content/data/AS/YE.json","name_iso_en":"Yemen"},{"route":"/EU","file_path":"content/data/EU.json","name_iso_en":"Europe"},{"route":"/EU/AL","file_path":"content/data/EU/AL.json","name_iso_en":"Albania"},{"route":"/EU/AD","file_path":"content/data/EU/AD.json","name_iso_en":"Andorra"},{"route":"/EU/AT","file_path":"content/data/EU/AT.json","name_iso_en":"Austria"},{"route":"/EU/BY","file_path":"content/data/EU/BY.json","name_iso_en":"Belarus"},{"route":"/EU/BE","file_path":"content/data/EU/BE.json","name_iso_en":"Belgium"},{"route":"/EU/BA","file_path":"content/data/EU/BA.json","name_iso_en":"Bosnia and Herzegovina"},{"route":"/EU/BG","file_path":"content/data/EU/BG.json","name_iso_en":"Bulgaria"},{"route":"/EU/HR","file_path":"content/data/EU/HR.json","name_iso_en":"Croatia"},{"route":"/EU/CZ","file_path":"content/data/EU/CZ.json","name_iso_en":"Czech Republic"},{"route":"/EU/DK","file_path":"content/data/EU/DK.json","name_iso_en":"Denmark"},{"route":"/EU/EE","file_path":"content/data/EU/EE.json","name_iso_en":"Estonia"},{"route":"/EU/FO","file_path":"content/data/EU/FO.json","name_iso_en":"Faroe Islands"},{"route":"/EU/FI","file_path":"content/data/EU/FI.json","name_iso_en":"Finland"},{"route":"/EU/FR","file_path":"content/data/EU/FR.json","name_iso_en":"France"},{"route":"/EU/DE","file_path":"content/data/EU/DE.json","name_iso_en":"Germany"},{"route":"/EU/GI","file_path":"content/data/EU/GI.json","name_iso_en":"Gibraltar"},{"route":"/EU/GR","file_path":"content/data/EU/GR.json","name_iso_en":"Greece"},{"route":"/EU/GG","file_path":"content/data/EU/GG.json","name_iso_en":"Guernsey"},{"route":"/EU/VA","file_path":"content/data/EU/VA.json","name_iso_en":"Holy See (Vatican City State)"},{"route":"/EU/HU","file_path":"content/data/EU/HU.json","name_iso_en":"Hungary"},{"route":"/EU/IS","file_path":"content/data/EU/IS.json","name_iso_en":"Iceland"},{"route":"/EU/IE","file_path":"content/data/EU/IE.json","name_iso_en":"Ireland"},{"route":"/EU/IM","file_path":"content/data/EU/IM.json","name_iso_en":"Isle of Man"},{"route":"/EU/IT","file_path":"content/data/EU/IT.json","name_iso_en":"Italy"},{"route":"/EU/JE","file_path":"content/data/EU/JE.json","name_iso_en":"Jersey"},{"route":"/EU/LV","file_path":"content/data/EU/LV.json","name_iso_en":"Latvia"},{"route":"/EU/LI","file_path":"content/data/EU/LI.json","name_iso_en":"Liechtenstein"},{"route":"/EU/LT","file_path":"content/data/EU/LT.json","name_iso_en":"Lithuania"},{"route":"/EU/LU","file_path":"content/data/EU/LU.json","name_iso_en":"Luxembourg"},{"route":"/EU/MK","file_path":"content/data/EU/MK.json","name_iso_en":"Macedonia, The Former Yugoslav Republic of"},{"route":"/EU/MT","file_path":"content/data/EU/MT.json","name_iso_en":"Malta"},{"route":"/EU/MD","file_path":"content/data/EU/MD.json","name_iso_en":"Moldova, Republic of"},{"route":"/EU/MC","file_path":"content/data/EU/MC.json","name_iso_en":"Monaco"},{"route":"/EU/ME","file_path":"content/data/EU/ME.json","name_iso_en":"Montenegro"},{"route":"/EU/NL","file_path":"content/data/EU/NL.json","name_iso_en":"Netherlands"},{"route":"/EU/NO","file_path":"content/data/EU/NO.json","name_iso_en":"Norway"},{"route":"/EU/PL","file_path":"content/data/EU/PL.json","name_iso_en":"Poland"},{"route":"/EU/PT","file_path":"content/data/EU/PT.json","name_iso_en":"Portugal"},{"route":"/EU/RO","file_path":"content/data/EU/RO.json","name_iso_en":"Romania"},{"route":"/EU/RU","file_path":"content/data/EU/RU.json","name_iso_en":"Russian Federation"},{"route":"/EU/SM","file_path":"content/data/EU/SM.json","name_iso_en":"San Marino"},{"route":"/EU/RS","file_path":"content/data/EU/RS.json","name_iso_en":"Serbia"},{"route":"/EU/SK","file_path":"content/data/EU/SK.json","name_iso_en":"Slovakia"},{"route":"/EU/SI","file_path":"content/data/EU/SI.json","name_iso_en":"Slovenia"},{"route":"/EU/ES","file_path":"content/data/EU/ES.json","name_iso_en":"Spain"},{"route":"/EU/SJ","file_path":"content/data/EU/SJ.json","name_iso_en":"Svalbard and Jan Mayen"},{"route":"/EU/SE","file_path":"content/data/EU/SE.json","name_iso_en":"Sweden"},{"route":"/EU/CH","file_path":"content/data/EU/CH.json","name_iso_en":"Switzerland"},{"route":"/EU/UA","file_path":"content/data/EU/UA.json","name_iso_en":"Ukraine"},{"route":"/EU/GB","file_path":"content/data/EU/GB.json","name_iso_en":"United Kingdom"},{"route":"/AF","file_path":"content/data/AF.json","name_iso_en":"Africa"},{"route":"/AF/AO","file_path":"content/data/AF/AO.json","name_iso_en":"Angola"},{"route":"/AF/BJ","file_path":"content/data/AF/BJ.json","name_iso_en":"Benin"},{"route":"/AF/BW","file_path":"content/data/AF/BW.json","name_iso_en":"Botswana"},{"route":"/AF/BF","file_path":"content/data/AF/BF.json","name_iso_en":"Burkina Faso"},{"route":"/AF/BI","file_path":"content/data/AF/BI.json","name_iso_en":"Burundi"},{"route":"/AF/CM","file_path":"content/data/AF/CM.json","name_iso_en":"Cameroon"},{"route":"/AF/CV","file_path":"content/data/AF/CV.json","name_iso_en":"Cape Verde"},{"route":"/AF/CF","file_path":"content/data/AF/CF.json","name_iso_en":"Central African Republic"},{"route":"/AF/TD","file_path":"content/data/AF/TD.json","name_iso_en":"Chad"},{"route":"/AF/KM","file_path":"content/data/AF/KM.json","name_iso_en":"Comoros"},{"route":"/AF/CG","file_path":"content/data/AF/CG.json","name_iso_en":"Congo"},{"route":"/AF/CD","file_path":"content/data/AF/CD.json","name_iso_en":"Congo, The Democratic Republic of the"},{"route":"/AF/CI","file_path":"content/data/AF/CI.json","name_iso_en":"Cote d'Ivoire"},{"route":"/AF/DJ","file_path":"content/data/AF/DJ.json","name_iso_en":"Djibouti"},{"route":"/AF/EG","file_path":"content/data/AF/EG.json","name_iso_en":"Egypt"},{"route":"/AF/GQ","file_path":"content/data/AF/GQ.json","name_iso_en":"Equatorial Guinea"},{"route":"/AF/ER","file_path":"content/data/AF/ER.json","name_iso_en":"Eritrea"},{"route":"/AF/ET","file_path":"content/data/AF/ET.json","name_iso_en":"Ethiopia"},{"route":"/AF/GA","file_path":"content/data/AF/GA.json","name_iso_en":"Gabon"},{"route":"/AF/GM","file_path":"content/data/AF/GM.json","name_iso_en":"Gambia"},{"route":"/AF/GH","file_path":"content/data/AF/GH.json","name_iso_en":"Ghana"},{"route":"/AF/GN","file_path":"content/data/AF/GN.json","name_iso_en":"Guinea"},{"route":"/AF/GW","file_path":"content/data/AF/GW.json","name_iso_en":"Guinea-Bissau"},{"route":"/AF/KE","file_path":"content/data/AF/KE.json","name_iso_en":"Kenya"},{"route":"/AF/LS","file_path":"content/data/AF/LS.json","name_iso_en":"Lesotho"},{"route":"/AF/LR","file_path":"content/data/AF/LR.json","name_iso_en":"Liberia"},{"route":"/AF/LY","file_path":"content/data/AF/LY.json","name_iso_en":"Libyan Arab Jamahiriya"},{"route":"/AF/MG","file_path":"content/data/AF/MG.json","name_iso_en":"Madagascar"},{"route":"/AF/MW","file_path":"content/data/AF/MW.json","name_iso_en":"Malawi"},{"route":"/AF/ML","file_path":"content/data/AF/ML.json","name_iso_en":"Mali"},{"route":"/AF/MR","file_path":"content/data/AF/MR.json","name_iso_en":"Mauritania"},{"route":"/AF/MU","file_path":"content/data/AF/MU.json","name_iso_en":"Mauritius"},{"route":"/AF/YT","file_path":"content/data/AF/YT.json","name_iso_en":"Mayotte"},{"route":"/AF/MA","file_path":"content/data/AF/MA.json","name_iso_en":"Morocco"},{"route":"/AF/MZ","file_path":"content/data/AF/MZ.json","name_iso_en":"Mozambique"},{"route":"/AF/NA","file_path":"content/data/AF/NA.json","name_iso_en":"Namibia"},{"route":"/AF/NE","file_path":"content/data/AF/NE.json","name_iso_en":"Niger"},{"route":"/AF/NG","file_path":"content/data/AF/NG.json","name_iso_en":"Nigeria"},{"route":"/AF/RE","file_path":"content/data/AF/RE.json","name_iso_en":"Reunion"},{"route":"/AF/RW","file_path":"content/data/AF/RW.json","name_iso_en":"Rwanda"},{"route":"/AF/SH","file_path":"content/data/AF/SH.json","name_iso_en":"Saint Helena, Ascension and Tristan da Cunha"},{"route":"/AF/ST","file_path":"content/data/AF/ST.json","name_iso_en":"Sao Tome and Principe"},{"route":"/AF/SN","file_path":"content/data/AF/SN.json","name_iso_en":"Senegal"},{"route":"/AF/SC","file_path":"content/data/AF/SC.json","name_iso_en":"Seychelles"},{"route":"/AF/SL","file_path":"content/data/AF/SL.json","name_iso_en":"Sierra Leone"},{"route":"/AF/SO","file_path":"content/data/AF/SO.json","name_iso_en":"Somalia"},{"route":"/AF/ZA","file_path":"content/data/AF/ZA.json","name_iso_en":"South Africa"},{"route":"/AF/SS","file_path":"content/data/AF/SS.json","name_iso_en":"South Sudan"},{"route":"/AF/SD","file_path":"content/data/AF/SD.json","name_iso_en":"Sudan"},{"route":"/AF/SZ","file_path":"content/data/AF/SZ.json","name_iso_en":"Swaziland"},{"route":"/AF/TZ","file_path":"content/data/AF/TZ.json","name_iso_en":"Tanzania, United Republic of"},{"route":"/AF/TG","file_path":"content/data/AF/TG.json","name_iso_en":"Togo"},{"route":"/AF/TN","file_path":"content/data/AF/TN.json","name_iso_en":"Tunisia"},{"route":"/AF/UG","file_path":"content/data/AF/UG.json","name_iso_en":"Uganda"},{"route":"/AF/EH","file_path":"content/data/AF/EH.json","name_iso_en":"Western Sahara"},{"route":"/AF/ZM","file_path":"content/data/AF/ZM.json","name_iso_en":"Zambia"},{"route":"/AF/ZW","file_path":"content/data/AF/ZW.json","name_iso_en":"Zimbabwe"},{"route":"/OC","file_path":"content/data/OC.json","name_iso_en":"Oceania"},{"route":"/OC/AU","file_path":"content/data/OC/AU.json","name_iso_en":"Australia"},{"route":"/OC/CK","file_path":"content/data/OC/CK.json","name_iso_en":"Cook Islands"},{"route":"/OC/FJ","file_path":"content/data/OC/FJ.json","name_iso_en":"Fiji"},{"route":"/OC/PF","file_path":"content/data/OC/PF.json","name_iso_en":"French Polynesia"},{"route":"/OC/GU","file_path":"content/data/OC/GU.json","name_iso_en":"Guam"},{"route":"/OC/HM","file_path":"content/data/OC/HM.json","name_iso_en":"Heard Island and McDonald Islands"},{"route":"/OC/KI","file_path":"content/data/OC/KI.json","name_iso_en":"Kiribati"},{"route":"/OC/MH","file_path":"content/data/OC/MH.json","name_iso_en":"Marshall Islands"},{"route":"/OC/FM","file_path":"content/data/OC/FM.json","name_iso_en":"Micronesia, Federated States of"},{"route":"/OC/NR","file_path":"content/data/OC/NR.json","name_iso_en":"Nauru"},{"route":"/OC/NC","file_path":"content/data/OC/NC.json","name_iso_en":"New Caledonia"},{"route":"/OC/NZ","file_path":"content/data/OC/NZ.json","name_iso_en":"New Zealand"},{"route":"/OC/NU","file_path":"content/data/OC/NU.json","name_iso_en":"Niue"},{"route":"/OC/NF","file_path":"content/data/OC/NF.json","name_iso_en":"Norfolk Island"},{"route":"/OC/MP","file_path":"content/data/OC/MP.json","name_iso_en":"Northern Mariana Islands"},{"route":"/OC/PW","file_path":"content/data/OC/PW.json","name_iso_en":"Palau"},{"route":"/OC/PG","file_path":"content/data/OC/PG.json","name_iso_en":"Papua New Guinea"},{"route":"/OC/PN","file_path":"content/data/OC/PN.json","name_iso_en":"Pitcairn"},{"route":"/OC/WS","file_path":"content/data/OC/WS.json","name_iso_en":"Samoa"},{"route":"/OC/SB","file_path":"content/data/OC/SB.json","name_iso_en":"Solomon Islands"},{"route":"/OC/TK","file_path":"content/data/OC/TK.json","name_iso_en":"Tokelau"},{"route":"/OC/TO","file_path":"content/data/OC/TO.json","name_iso_en":"Tonga"},{"route":"/OC/TV","file_path":"content/data/OC/TV.json","name_iso_en":"Tuvalu"},{"route":"/OC/UM","file_path":"content/data/OC/UM.json","name_iso_en":"United States Minor Outlying Islands"},{"route":"/OC/VU","file_path":"content/data/OC/VU.json","name_iso_en":"Vanuatu"},{"route":"/OC/WF","file_path":"content/data/OC/WF.json","name_iso_en":"Wallis and Futuna"}]